pyinitlib/__init__.py
pyinitlib-0.0.1.dist-info/licenses/LICENSE
pyinitlib-0.0.1.dist-info/METADATA
pyinitlib-0.0.1.dist-info/WHEEL
pyinitlib-0.0.1.dist-info/top_level.txt
pyinitlib-0.0.1.dist-info/RECORD
