Metadata-Version: 2.4
Name: pyinitlib
Version: 0.0.1
Summary: Une petite bibliothèque exemple nommée pyinitlib qui sert à initaliser vos application consoles en Python 3.X .
Author-email: Ton Nom <you@example.com>
License: MIT
License-File: LICENSE
Dynamic: license-file
